nun/__init__.py
nun/make_prayer.py
nun-1.1.0.dist-info/METADATA
nun-1.1.0.dist-info/WHEEL
nun-1.1.0.dist-info/licenses/LICENSE.txt
nun-1.1.0.dist-info/RECORD
